convert_trusted_gpg/__init__.py
convert_trusted_gpg-1.0.0.dist-info/METADATA
convert_trusted_gpg-1.0.0.dist-info/WHEEL
convert_trusted_gpg-1.0.0.dist-info/entry_points.txt
convert_trusted_gpg-1.0.0.dist-info/licenses/LICENSE
convert_trusted_gpg-1.0.0.dist-info/RECORD
