Metadata-Version: 2.1
Name: convert-trusted-gpg
Version: 1.0.0
Summary: Tool to convert apt trusted.gpg file into multiple trusted.gpg.d files
Project-URL: Homepage, https://github.com/gene1wood/convert-trusted-gpg
Project-URL: Bug Tracker, https://github.com/gene1wood/convert-trusted-gpg/issues
Author-email: Gene Wood <gene_wood@cementhorizon.com>
License-File: LICENSE
Classifier: Development Status :: 4 - Beta
Classifier: Environment :: Console
Classifier: Intended Audience :: System Administrators
Classifier: License :: OSI Approved :: GNU General Public License v3 or later (GPLv3+)
Classifier: Operating System :: POSIX :: Linux
Classifier: Programming Language :: Python :: 3
Requires-Python: >=3.7
